fmmpy/FMMModel.py
fmmpy/__init__.py
fmmpy/auxiliar_functions.py
fmmpy/fit_fmm.py
fmmpy/fit_fmm_k.py
fmmpy/fit_fmm_k_restr.py
fmmpy-1.0.0.dist-info/licenses/LICENSE
fmmpy-1.0.0.dist-info/METADATA
fmmpy-1.0.0.dist-info/WHEEL
fmmpy-1.0.0.dist-info/top_level.txt
fmmpy-1.0.0.dist-info/RECORD
