Metadata-Version: 2.4
Name: fmmpy
Version: 1.0.0
Summary: Frequency-Modulated Möbius decomposition for multichannel signals
Author: Rocío Carratalá-Sáez, Cristina Rueda
Author-email: Christian Canedo <christian.canedo@uva.es>
License:                     GNU GENERAL PUBLIC LICENSE
Project-URL: Homepage, https://github.com/FMMGroupVa/fmmpy
Project-URL: Repository, https://github.com/FMMGroupVa/fmmpy
Requires-Python: >=3.8
License-File: LICENSE
Requires-Dist: numpy>=1.25
Requires-Dist: scipy>=1.10
Requires-Dist: pandas>=1.5
Requires-Dist: numba>=0.57
Requires-Dist: qpsolvers>=3.0
Requires-Dist: matplotlib>=3.7
Requires-Dist: quadprog>=0.1.13
Dynamic: license-file
